pulumi_juniper_mist/__init__.py
pulumi_juniper_mist/_inputs.py
pulumi_juniper_mist/_utilities.py
pulumi_juniper_mist/get_const_alarms.py
pulumi_juniper_mist/get_const_app_categories.py
pulumi_juniper_mist/get_const_app_sub_categories.py
pulumi_juniper_mist/get_const_applications.py
pulumi_juniper_mist/get_const_countries.py
pulumi_juniper_mist/get_const_fingerprints.py
pulumi_juniper_mist/get_const_traffic_types.py
pulumi_juniper_mist/get_const_webhooks.py
pulumi_juniper_mist/get_sites.py
pulumi_juniper_mist/outputs.py
pulumi_juniper_mist/provider.py
pulumi_juniper_mist/pulumi-plugin.json
pulumi_juniper_mist/py.typed
pulumi_juniper_mist/upgrade_device.py
pulumi_juniper_mist/config/__init__.py
pulumi_juniper_mist/config/__init__.pyi
pulumi_juniper_mist/config/vars.py
pulumi_juniper_mist/device/__init__.py
pulumi_juniper_mist/device/_inputs.py
pulumi_juniper_mist/device/ap.py
pulumi_juniper_mist/device/base.py
pulumi_juniper_mist/device/gateway.py
pulumi_juniper_mist/device/gateway_cluster.py
pulumi_juniper_mist/device/get_ap_stats.py
pulumi_juniper_mist/device/get_gateway_stats.py
pulumi_juniper_mist/device/get_switch_stats.py
pulumi_juniper_mist/device/get_versions.py
pulumi_juniper_mist/device/image.py
pulumi_juniper_mist/device/outputs.py
pulumi_juniper_mist/device/switch.py
pulumi_juniper_mist/org/__init__.py
pulumi_juniper_mist/org/_inputs.py
pulumi_juniper_mist/org/alarmtemplate.py
pulumi_juniper_mist/org/apitoken.py
pulumi_juniper_mist/org/avprofile.py
pulumi_juniper_mist/org/base.py
pulumi_juniper_mist/org/deviceprofile_ap.py
pulumi_juniper_mist/org/deviceprofile_assign.py
pulumi_juniper_mist/org/deviceprofile_gateway.py
pulumi_juniper_mist/org/evpn_topology.py
pulumi_juniper_mist/org/gatewaytemplate.py
pulumi_juniper_mist/org/get_alarmtemplates.py
pulumi_juniper_mist/org/get_avprofiles.py
pulumi_juniper_mist/org/get_deviceprofiles_ap.py
pulumi_juniper_mist/org/get_deviceprofiles_gateway.py
pulumi_juniper_mist/org/get_evpn_topologies.py
pulumi_juniper_mist-0.7.1.dist-info/METADATA
pulumi_juniper_mist-0.7.1.dist-info/WHEEL
pulumi_juniper_mist-0.7.1.dist-info/top_level.txt
pulumi_juniper_mist-0.7.1.dist-info/RECORD
